{"chunk_definitions":[{"row":19,"row_count":1,"visible":true,"expansion_state":0,"options":{"engine":"r","label":"boxplot1","eval":true,"echo":false,"dev":"png"},"document_id":"0452480F","chunk_id":"cszgyvmtypag3","chunk_label":"boxplot1"},{"row":30,"row_count":1,"visible":true,"expansion_state":0,"options":{"engine":"r","label":"packages2","dev":"png"},"document_id":"0452480F","chunk_id":"cxctpueyh4jvd","chunk_label":"unnamed-chunk-1"},{"row":67,"row_count":1,"visible":true,"expansion_state":0,"options":{"engine":"r","label":"teoretical box plot","echo":true,"dev":"png"},"document_id":"0452480F","chunk_id":"cvwpxvribo3ew","chunk_label":"teoretical box plot"},{"row":86,"row_count":1,"visible":true,"expansion_state":0,"options":{"engine":"r","label":"boxplot_4_1","echo":true,"dev":"png"},"document_id":"0452480F","chunk_id":"cn2l0qzylozsj","chunk_label":"boxplot_4_1"},{"row":94,"row_count":1,"visible":true,"expansion_state":0,"options":{"engine":"r","label":"boxplot4-2","dev":"png"},"document_id":"0452480F","chunk_id":"ci5p71l6rret5","chunk_label":"unnamed-chunk-2"},{"row":102,"row_count":1,"visible":true,"expansion_state":0,"options":{"engine":"r","label":"boxplot4_3","dev":"png"},"document_id":"0452480F","chunk_id":"c2q5b0bz8exh8","chunk_label":"unnamed-chunk-3"},{"row":112,"row_count":1,"visible":true,"expansion_state":0,"options":{"engine":"r","label":"boxplot4-4","dev":"png"},"document_id":"0452480F","chunk_id":"c3p1bz3xcy4cd","chunk_label":"unnamed-chunk-4"},{"row":121,"row_count":1,"visible":true,"expansion_state":0,"options":{"engine":"r","label":"boxplot4-5","dev":"png"},"document_id":"0452480F","chunk_id":"chg9tgtva1hc7","chunk_label":"unnamed-chunk-5"},{"row":127,"row_count":1,"visible":true,"expansion_state":0,"options":{"engine":"r","label":"boxplot4-6","dev":"png"},"document_id":"0452480F","chunk_id":"ctfkj30qpri8k","chunk_label":"unnamed-chunk-6"},{"row":150,"row_count":1,"visible":true,"expansion_state":0,"options":{"engine":"r","label":"boxplot_flower","dev":"png"},"document_id":"0452480F","chunk_id":"c6fxe35b78ztm","chunk_label":"unnamed-chunk-7"},{"row":168,"row_count":1,"visible":true,"expansion_state":0,"options":{"engine":"r","echo":false,"eval":false,"label":"unnamed-chunk-77","dev":"png"},"document_id":"0452480F","chunk_id":"cd6zvldplo5rh","chunk_label":"unnamed-chunk-8"},{"row":209,"row_count":1,"visible":true,"expansion_state":0,"options":{"engine":"r","label":"geomviolin1","echo":true,"dev":"png"},"document_id":"0452480F","chunk_id":"chu41v3mw6q9y","chunk_label":"geomviolin1"},{"row":228,"row_count":1,"visible":true,"expansion_state":0,"options":{"engine":"r","label":"geomviolin2","dev":"png"},"document_id":"0452480F","chunk_id":"c99adf1mvrfqi","chunk_label":"geomviolin2"},{"row":246,"row_count":1,"visible":true,"expansion_state":0,"options":{"engine":"r","label":"unnamed-chunk-91","dev":"png"},"document_id":"0452480F","chunk_id":"ctxykom2dpu70","chunk_label":"unnamed-chunk-9"},{"row":282,"row_count":1,"visible":true,"expansion_state":0,"options":{"engine":"r","label":"geomviolin3","dev":"png"},"document_id":"0452480F","chunk_id":"c4ingpco022qe","chunk_label":"geomviolin3"},{"row":303,"row_count":1,"visible":true,"expansion_state":0,"options":{"engine":"r","label":"geomviolin4","dev":"png"},"document_id":"0452480F","chunk_id":"ckbvl6lfjgq03","chunk_label":"geomviolin4"},{"row":321,"row_count":1,"visible":true,"expansion_state":0,"options":{"engine":"r","label":"geomviolin5","dev":"png"},"document_id":"0452480F","chunk_id":"cxxqy5zuh6i1o","chunk_label":"geomviolin5"},{"row":338,"row_count":1,"visible":true,"expansion_state":0,"options":{"engine":"r","label":"geomviolin6","dev":"png"},"document_id":"0452480F","chunk_id":"cw23fhajwaql1","chunk_label":"geomviolin6"},{"row":357,"row_count":1,"visible":true,"expansion_state":0,"options":{"engine":"r","label":"geomviolin7","dev":"png"},"document_id":"0452480F","chunk_id":"cn1odzc4g3p1x","chunk_label":"geomviolin7"},{"row":374,"row_count":1,"visible":true,"expansion_state":0,"options":{"engine":"r","label":"geomviolin8","dev":"png"},"document_id":"0452480F","chunk_id":"cnxd3bcv9q3km","chunk_label":"geomviolin8"},{"row":393,"row_count":1,"visible":true,"expansion_state":0,"options":{"engine":"r","label":"geomviolin9","dev":"png"},"document_id":"0452480F","chunk_id":"civk8w2k4sx69","chunk_label":"geomviolin9"},{"row":411,"row_count":1,"visible":true,"expansion_state":0,"options":{"engine":"r","label":"geomviolin10","dev":"png"},"document_id":"0452480F","chunk_id":"crl4p99yncqjc","chunk_label":"geomviolin10"},{"row":435,"row_count":1,"visible":true,"expansion_state":0,"options":{"engine":"r","label":"unnamed-chunk-92","dev":"png"},"document_id":"0452480F","chunk_id":"che69zx0l8wpc","chunk_label":"unnamed-chunk-10"},{"row":461,"row_count":1,"visible":true,"expansion_state":0,"options":{"engine":"r","label":"unnamed-chunk-93","dev":"png"},"document_id":"0452480F","chunk_id":"c2fd8jdufgxvv","chunk_label":"unnamed-chunk-11"}],"doc_write_time":1735404775,"chunk_rendered_width":700}